workflow_nodes/__init__.py
workflow_nodes/main.py
workflow_nodes/utils.py
workflow_nodes/config/__init__.py
workflow_nodes/config/activate_autocompletion.py
workflow_nodes/config/main.py
workflow_nodes/converter/__init__.py
workflow_nodes/converter/excel_to_kadi.py
workflow_nodes/converter/file_converter.py
workflow_nodes/converter/kadi_to_kadi.py
workflow_nodes/converter/main.py
workflow_nodes/converter/merge_tables.py
workflow_nodes/converter/pace_to_kadi.py
workflow_nodes/converter/xml_to_kadi.py
workflow_nodes/debug/__init__.py
workflow_nodes/debug/main.py
workflow_nodes/debug/print_value.py
workflow_nodes/environment/__init__.py
workflow_nodes/environment/main.py
workflow_nodes/environment/mpirun.py
workflow_nodes/environment/screen.py
workflow_nodes/environment/ssh.py
workflow_nodes/excel/__init__.py
workflow_nodes/excel/excel_add_data.py
workflow_nodes/excel/excel_data.py
workflow_nodes/excel/excel_read_data.py
workflow_nodes/excel/main.py
workflow_nodes/excel/utils.py
workflow_nodes/misc/__init__.py
workflow_nodes/misc/compare_number.py
workflow_nodes/misc/compare_string.py
workflow_nodes/misc/create_qr_code.py
workflow_nodes/misc/create_symlink.py
workflow_nodes/misc/files_combine.py
workflow_nodes/misc/gmsh.py
workflow_nodes/misc/imagej_macro.py
workflow_nodes/misc/imagej_variable.py
workflow_nodes/misc/latexmk.py
workflow_nodes/misc/main.py
workflow_nodes/misc/matlab.py
workflow_nodes/misc/meshio_convert.py
workflow_nodes/misc/octave.py
workflow_nodes/misc/paraview_macro.py
workflow_nodes/misc/pvbatch.py
workflow_nodes/misc/random_value.py
workflow_nodes/misc/run_script.py
workflow_nodes/misc/send_mail.py
workflow_nodes/misc/tectonic.py
workflow_nodes/misc/xmllint.py
workflow_nodes/plot/__init__.py
workflow_nodes/plot/main.py
workflow_nodes/plot/plot_histo.py
workflow_nodes/plot/plot_matplotlib.py
workflow_nodes/plot/plot_veusz.py
workflow_nodes/repo/__init__.py
workflow_nodes/repo/collection_visualize.py
workflow_nodes/repo/main.py
workflow_nodes-0.22.0.dist-info/LICENSE
workflow_nodes-0.22.0.dist-info/METADATA
workflow_nodes-0.22.0.dist-info/WHEEL
workflow_nodes-0.22.0.dist-info/entry_points.txt
workflow_nodes-0.22.0.dist-info/top_level.txt
workflow_nodes-0.22.0.dist-info/RECORD
