Metadata-Version: 2.1
Name: workflow-nodes
Version: 0.22.0
Summary: Collection of tools for use in workflows
Author: Karlsruhe Institute of Technology
License: Apache-2.0
Project-URL: Documentation, https://workflow-nodes.readthedocs.io/en/stable
Project-URL: Source, https://gitlab.com/iam-cms/workflows/workflow-nodes
Project-URL: Changelog, https://gitlab.com/iam-cms/workflows/workflow-nodes/-/blob/master/HISTORY.md
Classifier: Development Status :: 4 - Beta
Classifier: License :: OSI Approved :: Apache Software License
Classifier: Operating System :: OS Independent
Classifier: Programming Language :: Python :: 3
Requires-Python: <3.14,>=3.9
License-File: LICENSE
Requires-Dist: click <9.0.0,>=8.0.0
Requires-Dist: defusedxml <1.0.0
Requires-Dist: graphviz <1.0.0
Requires-Dist: kadi-apy <0.44.0,>=0.43.0
Requires-Dist: matplotlib <4.0.0
Requires-Dist: openpyxl <4.0.0
Requires-Dist: pandas <3.0.0
Requires-Dist: pylatex <2.0.0,>=1.4.2
Requires-Dist: qrcode <9.0.0
Requires-Dist: scipy <2.0.0,>=1.5.1
Requires-Dist: xmlhelpy <0.15.0,>=0.14.0
Provides-Extra: all
Requires-Dist: workflow-nodes[ssh] ; extra == 'all'
Provides-Extra: dev
Requires-Dist: autoflake ==2.3.1 ; extra == 'dev'
Requires-Dist: black ==24.10.0 ; extra == 'dev'
Requires-Dist: build ==1.2.2.post1 ; extra == 'dev'
Requires-Dist: isort ==5.13.2 ; extra == 'dev'
Requires-Dist: myst-parser ==3.0.1 ; extra == 'dev'
Requires-Dist: pre-commit ==4.0.1 ; extra == 'dev'
Requires-Dist: pylint ==3.3.1 ; extra == 'dev'
Requires-Dist: Sphinx ==7.4.7 ; extra == 'dev'
Requires-Dist: sphinx-click ==6.0.0 ; extra == 'dev'
Requires-Dist: sphinx-rtd-theme ==3.0.1 ; extra == 'dev'
Requires-Dist: twine ==5.1.1 ; extra == 'dev'
Provides-Extra: ssh
Requires-Dist: paramiko <4.0.0 ; extra == 'ssh'
Requires-Dist: scp <1.0.0 ; extra == 'ssh'
